[
  {
    "ountryName": "World",
    "Gdp": "73454.49"
  },
  {
    "ountryName": "European Union",
    "Gdp": "17266.94"
  },
  {
    "ountryName": "USA",
    "Gdp": "16237.75"
  },
  {
    "ountryName": "China",
    "Gdp": "9020.31"
  },
  {
    "ountryName": "Japan",
    "Gdp": "5149.90"
  },
  {
    "ountryName": "Germany",
    "Gdp": "3597.97"
  },
  {
    "ountryName": "France",
    "Gdp": "2739.27"
  },
  {
    "ountryName": "Brazil",
    "Gdp": "2456.66"
  },
  {
    "ountryName": "United Kingdom",
    "Gdp": "2422.92"
  },
  {
    "ountryName": "Russia",
    "Gdp": "2213.57"
  },
  {
    "ountryName": "Italy",
    "Gdp": "2076.01"
  },
  {
    "ountryName": "India",
    "Gdp": "1972.84"
  },
  {
    "ountryName": "Canada",
    "Gdp": "1843.75"
  },
  {
    "ountryName": "Australia",
    "Gdp": "1589.12"
  },
  {
    "ountryName": "Mexico",
    "Gdp": "1274.97"
  },
  {
    "ountryName": "Republic of Korea",
    "Gdp": "1258.59"
  },
  {
    "ountryName": "Indonesia",
    "Gdp": "946.39"
  },
  {
    "ountryName": "Turkey",
    "Gdp": "851.82"
  },
  {
    "ountryName": "Saudi Arabia",
    "Gdp": "745.62"
  },
  {
    "ountryName": "Argentina",
    "Gdp": "498.70"
  },
  {
    "ountryName": "South Africa",
    "Gdp": "375.99"
  }
]